INT.v
module INT (
  input wire clk,     // Clock signal
  input wire reset,   // Reset signal
  input wire early,   // Early signal from PFD
  output reg [4:0] INT_OUT,
  output reg overflow,
  output reg underflow
);

  reg [4:0] integral = 5'b0;    // 5-bit accumulator
  reg [3:0] plusInt  = 4'b0010; // 4-bit +Int constant
  reg [3:0] minusInt = 4'b1010; // 4-bit -Int constant
 

  always @(posedge clk or posedge reset) begin
    
    overflow  <= 0;
    underflow <= 0;
    
    if (reset) begin           //integral <= (early) ? (integral + 1) * plusInt : (integral - 1) * minusInt;
      integral  <= 5'b0;       // Reset the accumulator to zero
      overflow  <= 0;
      underflow <= 0;
    end else if (early) begin
      if (integral < 5'b11111) begin       
       overflow  <= 1;     // overflow condition
       underflow <= 0;
       integral  <= integral + 1; // // Increment the accumulator for early condition
       INT_OUT   <= plusInt * integral;

      end else begin   // if (integral > 5'b11111), again overflow condition
          overflow <= 1;
	  INT_OUT   <= plusInt * integral; // integral = 5'b11111
          //integral <= 5'b00000;
	end
      end
    if (early != 1) begin
      if (integral > 5'b00000) begin
	  overflow  <= 0;
	  underflow <= 1;
	  integral  <= integral - 1;  // Decrement the accumulator for late condition
	  INT_OUT   <= minusInt * integral;
       end else begin    //if (integral < 5'b00000), again underflow condition
	  underflow <= 1;
	  INT_OUT   <= minusInt * integral; // integral = 5'b00000
	  //integral <= 5'b00000;
    end
   end
  end
    
endmodule

INT_tb.v
`timescale 1ns/10ps
`include "INT.v"

module INT_tb;
  reg clk;
  reg reset;
  reg early;

  wire overflow;
  wire underflow;
  
  wire [4:0] INT_OUT;

  INT dut (
    .clk(clk),
    .reset(reset),
    .early(early),
    .INT_OUT(INT_OUT),
    .overflow(overflow),
    .underflow(underflow)
  );

  initial begin
   $dumpfile("Integrator.vcd");
   $dumpvars;

   
    // Initialize inputs
    clk = 0;
    reset = 0;
    early = 0;
   
    // Apply reset
    reset = 1;
    #10 reset = 0;

    // Test case 1: Early condition, expect overflow
    early = 1;

    #10 early = 0;

    // Wait for overflow
    #20;

    // Test case 2: Late condition, expect underflow
    early = 0;

    #10 early = 1;
  
    // Wait for underflow
    #20;

    // Test case 3: No overflow or underflow
    early = 1;

    #10 early = 1;
   
    // Wait for stability
    #400;
    
    // Test case 4: No overflow or underflow
    early = 0;

    #10 early = 0;

    // Wait for stability
    #400;

    // Terminate simulation
    $finish;
  end

  // Clock generation
  always begin
    #5 clk = ~clk;
  end
endmodule

Integrator.vcd
$date
	Sun Oct 22 21:44:06 2023
$end
$version
	Icarus Verilog
$end
$timescale
	10ps
$end
$scope module INT_tb $end
$var wire 1 ! underflow $end
$var wire 1 " overflow $end
$var wire 5 # INT_OUT [4:0] $end
$var reg 1 $ clk $end
$var reg 1 % early $end
$var reg 1 & reset $end
$scope module dut $end
$var wire 1 $ clk $end
$var wire 1 % early $end
$var wire 1 & reset $end
$var reg 5 ' INT_OUT [4:0] $end
$var reg 5 ( integral [4:0] $end
$var reg 4 ) minusInt [3:0] $end
$var reg 1 " overflow $end
$var reg 4 * plusInt [3:0] $end
$var reg 1 ! underflow $end
$upscope $end
$upscope $end
$enddefinitions $end
#0
$dumpvars
b10 *
b1010 )
b0 (
b0 '
1&
0%
0$
b0 #
0"
1!
$end
#500
1!
1$
#1000
0$
1%
0&
#1500
b1 (
1"
0!
1$
#2000
0$
0%
#2500
b1010 #
b1010 '
b0 (
1!
0"
1$
#3000
0$
#3500
b0 #
b0 '
1!
1$
#4000
0$
#4500
1!
1$
#5000
0$
1%
#5500
b1 (
1"
0!
1$
#6000
0$
#6500
b10 #
b10 '
b10 (
1"
1$
#7000
0$
#7500
b100 #
b100 '
b11 (
1"
1$
#8000
0$
#8500
b110 #
b110 '
b100 (
1"
1$
#9000
0$
#9500
b1000 #
b1000 '
b101 (
1"
1$
#10000
0$
#10500
b1010 #
b1010 '
b110 (
1"
1$
#11000
0$
#11500
b1100 #
b1100 '
b111 (
1"
1$
#12000
0$
#12500
b1110 #
b1110 '
b1000 (
1"
1$
#13000
0$
#13500
b10000 #
b10000 '
b1001 (
1"
1$
#14000
0$
#14500
b10010 #
b10010 '
b1010 (
1"
1$
#15000
0$
#15500
b10100 #
b10100 '
b1011 (
1"
1$
#16000
0$
#16500
b10110 #
b10110 '
b1100 (
1"
1$
#17000
0$
#17500
b11000 #
b11000 '
b1101 (
1"
1$
#18000
0$
#18500
b11010 #
b11010 '
b1110 (
1"
1$
#19000
0$
#19500
b11100 #
b11100 '
b1111 (
1"
1$
#20000
0$
#20500
b11110 #
b11110 '
b10000 (
1"
1$
#21000
0$
#21500
b0 #
b0 '
b10001 (
1"
1$
#22000
0$
#22500
b10 #
b10 '
b10010 (
1"
1$
#23000
0$
#23500
b100 #
b100 '
b10011 (
1"
1$
#24000
0$
#24500
b110 #
b110 '
b10100 (
1"
1$
#25000
0$
#25500
b1000 #
b1000 '
b10101 (
1"
1$
#26000
0$
#26500
b1010 #
b1010 '
b10110 (
1"
1$
#27000
0$
#27500
b1100 #
b1100 '
b10111 (
1"
1$
#28000
0$
#28500
b1110 #
b1110 '
b11000 (
1"
1$
#29000
0$
#29500
b10000 #
b10000 '
b11001 (
1"
1$
#30000
0$
#30500
b10010 #
b10010 '
b11010 (
1"
1$
#31000
0$
#31500
b10100 #
b10100 '
b11011 (
1"
1$
#32000
0$
#32500
b10110 #
b10110 '
b11100 (
1"
1$
#33000
0$
#33500
b11000 #
b11000 '
b11101 (
1"
1$
#34000
0$
#34500
b11010 #
b11010 '
b11110 (
1"
1$
#35000
0$
#35500
b11100 #
b11100 '
b11111 (
1"
1$
#36000
0$
#36500
b11110 #
b11110 '
1"
1$
#37000
0$
#37500
1"
1$
#38000
0$
#38500
1"
1$
#39000
0$
#39500
1"
1$
#40000
0$
#40500
1"
1$
#41000
0$
#41500
1"
1$
#42000
0$
#42500
1"
1$
#43000
0$
#43500
1"
1$
#44000
0$
#44500
1"
1$
#45000
0$
#45500
1"
1$
#46000
0$
#46500
1"
1$
#47000
0$
#47500
1"
1$
#48000
0$
0%
#48500
b10110 #
b10110 '
b11110 (
1!
0"
1$
#49000
0$
#49500
b1100 #
b1100 '
b11101 (
1!
1$
#50000
0$
#50500
b10 #
b10 '
b11100 (
1!
1$
#51000
0$
#51500
b11000 #
b11000 '
b11011 (
1!
1$
#52000
0$
#52500
b1110 #
b1110 '
b11010 (
1!
1$
#53000
0$
#53500
b100 #
b100 '
b11001 (
1!
1$
#54000
0$
#54500
b11010 #
b11010 '
b11000 (
1!
1$
#55000
0$
#55500
b10000 #
b10000 '
b10111 (
1!
1$
#56000
0$
#56500
b110 #
b110 '
b10110 (
1!
1$
#57000
0$
#57500
b11100 #
b11100 '
b10101 (
1!
1$
#58000
0$
#58500
b10010 #
b10010 '
b10100 (
1!
1$
#59000
0$
#59500
b1000 #
b1000 '
b10011 (
1!
1$
#60000
0$
#60500
b11110 #
b11110 '
b10010 (
1!
1$
#61000
0$
#61500
b10100 #
b10100 '
b10001 (
1!
1$
#62000
0$
#62500
b1010 #
b1010 '
b10000 (
1!
1$
#63000
0$
#63500
b0 #
b0 '
b1111 (
1!
1$
#64000
0$
#64500
b10110 #
b10110 '
b1110 (
1!
1$
#65000
0$
#65500
b1100 #
b1100 '
b1101 (
1!
1$
#66000
0$
#66500
b10 #
b10 '
b1100 (
1!
1$
#67000
0$
#67500
b11000 #
b11000 '
b1011 (
1!
1$
#68000
0$
#68500
b1110 #
b1110 '
b1010 (
1!
1$
#69000
0$
#69500
b100 #
b100 '
b1001 (
1!
1$
#70000
0$
#70500
b11010 #
b11010 '
b1000 (
1!
1$
#71000
0$
#71500
b10000 #
b10000 '
b111 (
1!
1$
#72000
0$
#72500
b110 #
b110 '
b110 (
1!
1$
#73000
0$
#73500
b11100 #
b11100 '
b101 (
1!
1$
#74000
0$
#74500
b10010 #
b10010 '
b100 (
1!
1$
#75000
0$
#75500
b1000 #
b1000 '
b11 (
1!
1$
#76000
0$
#76500
b11110 #
b11110 '
b10 (
1!
1$
#77000
0$
#77500
b10100 #
b10100 '
b1 (
1!
1$
#78000
0$
#78500
b1010 #
b1010 '
b0 (
1!
1$
#79000
0$
#79500
b0 #
b0 '
1!
1$
#80000
0$
#80500
1!
1$
#81000
0$
#81500
1!
1$
#82000
0$
#82500
1!
1$
#83000
0$
#83500
1!
1$
#84000
0$
#84500
1!
1$
#85000
0$
#85500
1!
1$
#86000
0$
#86500
1!
1$
#87000
0$
#87500
1!
1$
#88000
0$
#88500
1!
1$
